BeginnersbookCYuyanShiliChuyi/README.md
BeginnersbookCYuyanShiliChuyi/__init__.py
BeginnersbookCYuyanShiliChuyi/__main__.py
BeginnersbookCYuyanShiliChuyi/file.epub
BeginnersbookCYuyanShiliChuyi/index.html
BeginnersbookCYuyanShiliChuyi/css/__init__.py
BeginnersbookCYuyanShiliChuyi/css/annotations.css
BeginnersbookCYuyanShiliChuyi/css/main.css
BeginnersbookCYuyanShiliChuyi/css/normalize.css
BeginnersbookCYuyanShiliChuyi/css/popup.css
BeginnersbookCYuyanShiliChuyi/font/__init__.py
BeginnersbookCYuyanShiliChuyi/font/fontello.eot
BeginnersbookCYuyanShiliChuyi/font/fontello.svg
BeginnersbookCYuyanShiliChuyi/font/fontello.ttf
BeginnersbookCYuyanShiliChuyi/font/fontello.woff
BeginnersbookCYuyanShiliChuyi/img/__init__.py
BeginnersbookCYuyanShiliChuyi/img/annotator-glyph-sprite.png
BeginnersbookCYuyanShiliChuyi/img/annotator-icon-sprite.png
BeginnersbookCYuyanShiliChuyi/img/apple-touch-icon.png
BeginnersbookCYuyanShiliChuyi/img/cancelfullscreen.png
BeginnersbookCYuyanShiliChuyi/img/close.png
BeginnersbookCYuyanShiliChuyi/img/fullscreen.png
BeginnersbookCYuyanShiliChuyi/img/loader.gif
BeginnersbookCYuyanShiliChuyi/img/menu-icon.png
BeginnersbookCYuyanShiliChuyi/img/save.png
BeginnersbookCYuyanShiliChuyi/img/saved.png
BeginnersbookCYuyanShiliChuyi/img/settings-s.png
BeginnersbookCYuyanShiliChuyi/img/settings.png
BeginnersbookCYuyanShiliChuyi/img/star.png
BeginnersbookCYuyanShiliChuyi/js/__init__.py
BeginnersbookCYuyanShiliChuyi/js/epub.js
BeginnersbookCYuyanShiliChuyi/js/epub.min.js
BeginnersbookCYuyanShiliChuyi/js/epub.min.map
BeginnersbookCYuyanShiliChuyi/js/hooks.min.js
BeginnersbookCYuyanShiliChuyi/js/hooks.min.map
BeginnersbookCYuyanShiliChuyi/js/reader.js
BeginnersbookCYuyanShiliChuyi/js/reader.js.map
BeginnersbookCYuyanShiliChuyi/js/reader.min.js
BeginnersbookCYuyanShiliChuyi/js/reader.min.map
BeginnersbookCYuyanShiliChuyi/js/hooks/__init__.py
BeginnersbookCYuyanShiliChuyi/js/hooks/extensions/__init__.py
BeginnersbookCYuyanShiliChuyi/js/hooks/extensions/highlight.js
beginnersbook_c_yuyan_shili_chuyi-2024.3.4.0.dist-info/METADATA
beginnersbook_c_yuyan_shili_chuyi-2024.3.4.0.dist-info/WHEEL
beginnersbook_c_yuyan_shili_chuyi-2024.3.4.0.dist-info/entry_points.txt
beginnersbook_c_yuyan_shili_chuyi-2024.3.4.0.dist-info/top_level.txt
beginnersbook_c_yuyan_shili_chuyi-2024.3.4.0.dist-info/RECORD
